Workbook

Sheet Resumen
A1: Simulación de Promoción 10% OFF
A3: Categoría | B3: SKUs | C3: Precio Justo Total | D3: Precio c/Promo Total | E3: Descuento Total | F3: Utilidad c/Promo | G3: Margen Real Prom.
A4: Cervezas | B4: 238 | C4: =Cervezas!G240 -> 102938.16 | D4: =Cervezas!I240 -> 92644.344 | E4: =Cervezas!J240 -> 10293.816 | F4: =Cervezas!L240 -> 14888.818 | G4: =Cervezas!M240 -> 0.26261343
A5: Limpieza | B5: 41 | C5: =Limpieza!G43 -> 2787.76 | D5: =Limpieza!I43 -> 2508.984 | E5: =Limpieza!J43 -> 278.776 | F5: =Limpieza!L43 -> 559.95428 | G5: =Limpieza!M43 -> 0.25721086
A6: Nota: El descuento se aplica al PRECIO JUSTO (con impuestos). El margen real muestra la rentabilidad efectiva tras el descuento. El descuento (celda azul en cada hoja) es editable para simular otros %.

Sheet Cervezas
A1: STORE_ID | B1: SKU + Nombre | C1: COSTO | D1: IEPS | E1: IVA | F1: MARGEN | G1: PRECIO JUSTO | H1: DESCUENTO | I1: PRECIO FINAL C/PROMO | J1: MONTO DESCUENTO | K1: BASE S/IMP C/PROMO | L1: UTILIDAD C/PROMO | M1: MARGEN REAL C/PROMO | N1: DELTA MARGEN
A2: 9 | B2: 14381 - Ron Antillano Blanco 1L | C2: 46.77 | D2: 53 | E2: 16 | F2: 30 | G2: 118.57 | H2: 0.1 | I2: =G2*(1-H2) -> 106.713 | J2: =G2-I2 -> 11.857 | K2: =I2/((1+D2/100)*(1+E2/100)) -> 60.126775 | L2: =K2-C2 -> 13.356775 | M2: =IF(K2=0,0,L2/K2) -> 0.22214354 | N2: =M2-F2/100 -> -0.077856456
A3: 9 | B3: 19385 - Whisky William Lawson's Blended 700ml | C3: 71.37 | D3: 53 | E3: 16 | F3: 30 | G3: 180.96 | H3: 0.1 | I3: =G3*(1-H3) -> 162.864 | J3: =G3-I3 -> 18.096 | K3: =I3/((1+D3/100)*(1+E3/100)) -> 91.764706 | L3: =K3-C3 -> 20.394706 | M3: =IF(K3=0,0,L3/K3) -> 0.22225 | N3: =M3-F3/100 -> -0.07775
A4: 9 | B4: 23036 - Ron Bacardí Reserva 8 Años 750ml | C4: 250.73 | D4: 53 | E4: 16 | F4: 30 | G4: 635.72 | H4: 0.1 | I4: =G4*(1-H4) -> 572.148 | J4: =G4-I4 -> 63.572 | K4: =I4/((1+D4/100)*(1+E4/100)) -> 322.37323 | L4: =K4-C4 -> 71.643225 | M4: =IF(K4=0,0,L4/K4) -> 0.2222369 | N4: =M4-F4/100 -> -0.077763103
A5: 9 | B5: 17770 - Tequila Hornitos Cristalino 750ml | C5: 242.96 | D5: 53 | E5: 16 | F5: 35.03 | G5: 663.7 | H5: 0.1 | I5: =G5*(1-H5) -> 597.33 | J5: =G5-I5 -> 66.37 | K5: =I5/((1+D5/100)*(1+E5/100)) -> 336.56187 | L5: =K5-C5 -> 93.601866 | M5: =IF(K5=0,0,L5/K5) -> 0.27811192 | N5: =M5-F5/100 -> -0.072188082
A6: 9 | B6: 30116 - Ron Bacardí Blanco 700ml | C6: 98.6 | D6: 53 | E6: 16 | F6: 33.09 | G6: 261.53 | H6: 0.1 | I6: =G6*(1-H6) -> 235.377 | J6: =G6-I6 -> 26.153 | K6: =I6/((1+D6/100)*(1+E6/100)) -> 132.6217 | L6: =K6-C6 -> 34.021704 | M6: =IF(K6=0,0,L6/K6) -> 0.25653195 | N6: =M6-F6/100 -> -0.074368053
A7: 9 | B7: 17774 - Tequila Tres Generaciones Cristalino 750ml | C7: 405.23 | D7: 53 | E7: 16 | F7: 30 | G7: 1027.43 | H7: 0.1 | I7: =G7*(1-H7) -> 924.687 | J7: =G7-I7 -> 102.743 | K7: =I7/((1+D7/100)*(1+E7/100)) -> 521.00913 | L7: =K7-C7 -> 115.77913 | M7: =IF(K7=0,0,L7/K7) -> 0.22222092 | N7: =M7-F7/100 -> -0.07777908
A8: 9 | B8: 18748 - Vino Blanco Izadi Larrosa Blanca 750ml | C8: 183.73 | D8: 27 | E8: 16 | F8: 33.25 | G8: 405.5 | H8: 0.1 | I8: =G8*(1-H8) -> 364.95 | J8: =G8-I8 -> 40.55 | K8: =I8/((1+D8/100)*(1+E8/100)) -> 247.72604 | L8: =K8-C8 -> 63.996039 | M8: =IF(K8=0,0,L8/K8) -> 0.25833392 | N8: =M8-F8/100 -> -0.07416608
A9: 9 | B9: 31130 - Licor de Ron Bacardí Mango con Chile 700ml | C9: 91.84 | D9: 53 | E9: 16 | F9: 30 | G9: 232.85 | H9: 0.1 | I9: =G9*(1-H9) -> 209.565 | J9: =G9-I9 -> 23.285 | K9: =I9/((1+D9/100)*(1+E9/100)) -> 118.07809 | L9: =K9-C9 -> 26.238093 | M9: =IF(K9=0,0,L9/K9) -> 0.22220966 | N9: =M9-F9/100 -> -0.077790337
A10: 9 | B10: 18201 - Brandy Torres Winter Fruits 700ml | C10: 127 | D10: 53 | E10: 16 | F10: 38.68 | G10: 367.58 | H10: 0.1 | I10: =G10*(1-H10) -> 330.822 | J10: =G10-I10 -> 36.758 | K10: =I10/((1+D10/100)*(1+E10/100)) -> 186.39959 | L10: =K10-C10 -> 59.399594 | M10: =IF(K10=0,0,L10/K10) -> 0.31866805 | N10: =M10-F10/100 -> -0.068131955
A11: 9 | B11: 18166 - Licor Vaccari Sambuca 700ml | C11: 159.64 | D11: 53 | E11: 16 | F11: 39.22 | G11: 466.15 | H11: 0.1 | I11: =G11*(1-H11) -> 419.535 | J11: =G11-I11 -> 46.615 | K11: =I11/((1+D11/100)*(1+E11/100)) -> 236.38438 | L11: =K11-C11 -> 76.744381 | M11: =IF(K11=0,0,L11/K11) -> 0.32465927 | N11: =M11-F11/100 -> -0.067540727
A12: 9 | B12: 25906 - Licor de Mezcal Mitre Origen Oaxaca Tamborines 750ml | C12: 134.8 | D12: 53 | E12: 16 | F12: 36.78 | G12: 378.42 | H12: 0.1 | I12: =G12*(1-H12) -> 340.578 | J12: =G12-I12 -> 37.842 | K12: =I12/((1+D12/100)*(1+E12/100)) -> 191.89655 | L12: =K12-C12 -> 57.096552 | M12: =IF(K12=0,0,L12/K12) -> 0.29753819 | N12: =M12-F12/100 -> -0.070261815
A13: 9 | B13: 19732 - Vino Blanco Louis Jadot Bourgogne Chardonnay 750ml | C13: 339.65 | D13: 27 | E13: 16 | F13: 30 | G13: 714.81 | H13: 0.1 | I13: =G13*(1-H13) -> 643.329 | J13: =G13-I13 -> 71.481 | K13: =I13/((1+D13/100)*(1+E13/100)) -> 436.68816 | L13: =K13-C13 -> 97.038162 | M13: =IF(K13=0,0,L13/K13) -> 0.22221386 | N13: =M13-F13/100 -> -0.077786141
... A237: 14 | B237: 31390 - Tequila La Santa Black Añejo 100% 750ml | C237: 1076.18 | D237: 53 | E237: 16 | F237: 35.04 | G237: 2940.28 | H237: 0.1 | I237: =G237*(1-H237) -> 2646.252 | J237: =G237-I237 -> 294.028 | K237: =I237/((1+D237/100)*(1+E237/100)) -> 1491.0142 | L237: =K237-C237 -> 414.8342 | M237: =IF(K237=0,0,L237/K237) -> 0.27822284 | N237: =M237-F237/100 -> -0.072177164
H238: 0.1 | I238: =G238*(1-H238) -> 0 | J238: =G238-I238 -> 0 | K238: =I238/((1+D238/100)*(1+E238/100)) -> 0 | L238: =K238-C238 -> 0 | M238: =IF(K238=0,0,L238/K238) -> 0 | N238: =M238-F238/100 -> 0
A239: Filtros aplicados: DEPARTMENT es Cervezas, Vinos y Licores WAREHOUSE_ID es 9 TAG_MARGEN es 30% - 40% STATUS no es (En blanco) | H239: 0.1 | I239: =G239*(1-H239) -> 0 | J239: =G239-I239 -> 0 | K239: =I239/((1+D239/100)*(1+E239/100)) -> 0 | L239: =K239-C239 -> 0 | M239: =IF(K239=0,0,L239/K239) -> 0 | N239: =M239-F239/100 -> 0
B240: TOTALES / PROMEDIO | F240: =AVERAGE(F2:F239) -> 33.226695 | G240: =SUM(G2:G239) -> 102938.16 | I240: =SUM(I2:I239) -> 92644.344 | J240: =SUM(J2:J239) -> 10293.816 | L240: =SUM(L2:L239) -> 14888.818 | M240: =IF(SUM(K2:K239)=0,0,SUM(L2:L239)/SUM(K2:K239)) -> 0.26261343

Sheet Limpieza
A1: STORE_ID | B1: SKU + Nombre | C1: COSTO | D1: IEPS | E1: IVA | F1: MARGEN | G1: PRECIO JUSTO | H1: DESCUENTO | I1: PRECIO FINAL C/PROMO | J1: MONTO DESCUENTO | K1: BASE S/IMP C/PROMO | L1: UTILIDAD C/PROMO | M1: MARGEN REAL C/PROMO | N1: DELTA MARGEN
A2: 9 | B2: 12315 - Laminitas Raid Doble Acción 16 pzs | C2: 29.75 | D2: 0 | E2: 16 | F2: 31.05 | G2: 50.05 | H2: 0.1 | I2: =G2*(1-H2) -> 45.045 | J2: =G2-I2 -> 5.005 | K2: =I2/((1+D2/100)*(1+E2/100)) -> 38.831897 | L2: =K2-C2 -> 9.0818966 | M2: =IF(K2=0,0,L2/K2) -> 0.23387723 | N2: =M2-F2/100 -> -0.076622766
A3: 9 | B3: 12593 - Pila D Duracell 2 pzs | C3: 99.36 | D3: 0 | E3: 16 | F3: 35.37 | G3: 178.34 | H3: 0.1 | I3: =G3*(1-H3) -> 160.506 | J3: =G3-I3 -> 17.834 | K3: =I3/((1+D3/100)*(1+E3/100)) -> 138.36724 | L3: =K3-C3 -> 39.007241 | M3: =IF(K3=0,0,L3/K3) -> 0.28191096 | N3: =M3-F3/100 -> -0.071789043
A4: 9 | B4: 16157 - Toallitas Desinfectantes Cloralex sin Cloro 48 pzas | C4: 38.66 | D4: 0 | E4: 16 | F4: 30.29 | G4: 64.33 | H4: 0.1 | I4: =G4*(1-H4) -> 57.897 | J4: =G4-I4 -> 6.433 | K4: =I4/((1+D4/100)*(1+E4/100)) -> 49.911207 | L4: =K4-C4 -> 11.251207 | M4: =IF(K4=0,0,L4/K4) -> 0.22542446 | N4: =M4-F4/100 -> -0.077475539
A5: 9 | B5: 18367 - Lavatrastes Líquido Kuxtal Biodegradable 820ml | C5: 47.67 | D5: 0 | E5: 16 | F5: 31.85 | G5: 81.14 | H5: 0.1 | I5: =G5*(1-H5) -> 73.026 | J5: =G5-I5 -> 8.114 | K5: =I5/((1+D5/100)*(1+E5/100)) -> 62.953448 | L5: =K5-C5 -> 15.283448 | M5: =IF(K5=0,0,L5/K5) -> 0.24277381 | N5: =M5-F5/100 -> -0.075726193
A6: 9 | B6: 14342 - Limpiador Líquido Vidrios Superficies Windex Repuesto 500ml | C6: 19.79 | D6: 0 | E6: 16 | F6: 31.37 | G6: 33.45 | H6: 0.1 | I6: =G6*(1-H6) -> 30.105 | J6: =G6-I6 -> 3.345 | K6: =I6/((1+D6/100)*(1+E6/100)) -> 25.952586 | L6: =K6-C6 -> 6.1625862 | M6: =IF(K6=0,0,L6/K6) -> 0.23745557 | N6: =M6-F6/100 -> -0.076244428
A7: 9 | B7: 24709 - Limpiador para Baño Mr. Músculo Platinum Repuesto 500ml | C7: 19.07 | D7: 0 | E7: 16 | F7: 34.15 | G7: 33.59 | H7: 0.1 | I7: =G7*(1-H7) -> 30.231 | J7: =G7-I7 -> 3.359 | K7: =I7/((1+D7/100)*(1+E7/100)) -> 26.061207 | L7: =K7-C7 -> 6.9912069 | M7: =IF(K7=0,0,L7/K7) -> 0.26826106 | N7: =M7-F7/100 -> -0.073238943
A8: 9 | B8: 15579 - Fibra Grande Scotch-Brite 1pza | C8: 12.44 | D8: 0 | E8: 16 | F8: 34.9 | G8: 22.17 | H8: 0.1 | I8: =G8*(1-H8) -> 19.953 | J8: =G8-I8 -> 2.217 | K8: =I8/((1+D8/100)*(1+E8/100)) -> 17.200862 | L8: =K8-C8 -> 4.7608621 | M8: =IF(K8=0,0,L8/K8) -> 0.27678043 | N8: =M8-F8/100 -> -0.072219566
A9: 9 | B9: 12302 - Pañuelos Desechables Kleenex 3x70 pzs | C9: 36.95 | D9: 0 | E9: 16 | F9: 30.7 | G9: 61.85 | H9: 0.1 | I9: =G9*(1-H9) -> 55.665 | J9: =G9-I9 -> 6.185 | K9: =I9/((1+D9/100)*(1+E9/100)) -> 47.987069 | L9: =K9-C9 -> 11.037069 | M9: =IF(K9=0,0,L9/K9) -> 0.2300009 | N9: =M9-F9/100 -> -0.076999102
A10: 9 | B10: 13492 - Insecticida Raid Max Cucarachas e Insectos Rastreros 400ml | C10: 69.28 | D10: 0 | E10: 16 | F10: 30.31 | G10: 115.32 | H10: 0.1 | I10: =G10*(1-H10) -> 103.788 | J10: =G10-I10 -> 11.532 | K10: =I10/((1+D10/100)*(1+E10/100)) -> 89.472414 | L10: =K10-C10 -> 20.192414 | M10: =IF(K10=0,0,L10/K10) -> 0.22568312 | N10: =M10-F10/100 -> -0.077416877
A11: 9 | B11: 30515 - Pastillas para Tanque Cloralex Frescura Azul 160g | C11: 43.43 | D11: 0 | E11: 16 | F11: 30.41 | G11: 72.4 | H11: 0.1 | I11: =G11*(1-H11) -> 65.16 | J11: =G11-I11 -> 7.24 | K11: =I11/((1+D11/100)*(1+E11/100)) -> 56.172414 | L11: =K11-C11 -> 12.742414 | M11: =IF(K11=0,0,L11/K11) -> 0.22684469 | N11: =M11-F11/100 -> -0.07725531
A12: 9 | B12: 26838 - Escoba Reynera Básica 1 pz | C12: 47 | D12: 0 | E12: 16 | F12: 30.77 | G12: 78.75 | H12: 0.1 | I12: =G12*(1-H12) -> 70.875 | J12: =G12-I12 -> 7.875 | K12: =I12/((1+D12/100)*(1+E12/100)) -> 61.099138 | L12: =K12-C12 -> 14.099138 | M12: =IF(K12=0,0,L12/K12) -> 0.23075838 | N12: =M12-F12/100 -> -0.076941623
A13: 9 | B13: 27347 - Repuesto Aromatizante Glade Paraíso Azul y Hawaiian 5x21ml | C13: 175.11 | D13: 0 | E13: 16 | F13: 37.16 | G13: 323.25 | H13: 0.1 | I13: =G13*(1-H13) -> 290.925 | J13: =G13-I13 -> 32.325 | K13: =I13/((1+D13/100)*(1+E13/100)) -> 250.79741 | L13: =K13-C13 -> 75.687414 | M13: =IF(K13=0,0,L13/K13) -> 0.30178706 | N13: =M13-F13/100 -> -0.069812941
... A40: 14 | B40: 16294 - Fósforos Flama 50x10 pzas | C40: 16.2 | D40: 0 | E40: 16 | F40: 30.39 | G40: 26.99 | H40: 0.1 | I40: =G40*(1-H40) -> 24.291 | J40: =G40-I40 -> 2.699 | K40: =I40/((1+D40/100)*(1+E40/100)) -> 20.940517 | L40: =K40-C40 -> 4.7405172 | M40: =IF(K40=0,0,L40/K40) -> 0.22638014 | N40: =M40-F40/100 -> -0.077519859
H41: 0.1 | I41: =G41*(1-H41) -> 0 | J41: =G41-I41 -> 0 | K41: =I41/((1+D41/100)*(1+E41/100)) -> 0 | L41: =K41-C41 -> 0 | M41: =IF(K41=0,0,L41/K41) -> 0 | N41: =M41-F41/100 -> 0
A42: Filtros aplicados: DEPARTMENT es Limpieza y Hogar WAREHOUSE_ID es 9 TAG_MARGEN es 30% - 40% TAG_ROTACION es Alta rotacion o Rotacion normal STATUS no es (En blanco) | H42: 0.1 | I42: =G42*(1-H42) -> 0 | J42: =G42-I42 -> 0 | K42: =I42/((1+D42/100)*(1+E42/100)) -> 0 | L42: =K42-C42 -> 0 | M42: =IF(K42=0,0,L42/K42) -> 0 | N42: =M42-F42/100 -> 0
B43: TOTALES / PROMEDIO | F43: =AVERAGE(F2:F42) -> 32.467179 | G43: =SUM(G2:G42) -> 2787.76 | I43: =SUM(I2:I42) -> 2508.984 | J43: =SUM(J2:J42) -> 278.776 | L43: =SUM(L2:L42) -> 559.95428 | M43: =IF(SUM(K2:K42)=0,0,SUM(L2:L42)/SUM(K2:K42)) -> 0.25721086

Sheet GENRAL
A1: STORE_ID | B1: SKU | C1: Nombre | D1: Departamento | E1: Categoria | F1: COSTO | G1: IEPS | H1: IVA | I1: MARGEN | J1: PRECIO JUSTO | K1: TAG_MARGEN | L1: INDEX PRECIO DCTO | M1: PRECIO COMP DCTO | N1: PRECIO COMP LINEA | O1: INDEX PRECIO LINEA | P1: TAG_ROTACION | Q1: TAG_SHARE | R1: TAG ELAS | S1: ROTACION_REAL_RATIO | T1: DIAS_ENTRE_VENTA_SKU_TIENDA | U1: DIAS_ENTRE_VENTA_CATEGORIA_BASELINE | V1: FUENTE_BASELINE_CATEGORIA | W1: PROMO ACTIVA HOY | X1: TEMA_MUNDIAL | Y1: MOTIVO_SIN_OFERTA | Z1: REQUIERE_APROBACION | AA1: REQUIERE_REVISION_PESO_VARIABLE | AB1: DMAX_REAL_% | AC1: ESTRATEGIA | AD1: DIA_EJECUCION | AE1: PRECIO_OFERTA | AF1: DESC_EFECTIVO_% | AG1: MARGEN_OFERTA_% | AH1: FUENTE_ELASTICIDAD | AI1: FUENTE_Q0 | AJ1: CONFIANZA_PROYECCION | AK1: REDENCION | AL1: ELASTICIDAD_FINAL | AM1: UPLIFT_% | AN1: Q0_DIA | AO1: Q1_DIA | AP1: GMV_BASE_DIA | AQ1: GMV_PROY_DIA | AR1: GMV_INC_DIA | AS1: UTIL_BASE_DIA | AT1: UTIL_PROY_DIA | AU1: UTIL_INC_DIA
A2: 9 | B2: 14258 | C2: Cereal Kellogg's Choco Krispis Original 290g | D2: Despensa | E2: Cereales y Barras | F2: 37.39 | G2: 8 | H2: 0 | I2: 37.66 | J2: 64.78 | K2: 30% - 40% | L2: Mas caro | M2: 47.99 | N2: 56 | O2: Mas caro | P2: Alta rotacion | Q2: ALTO SHARE | R2: POCO ELASTICO | S2: 3.79 | T2: 1.3 | U2: 4.9 | V2: Categoria x tienda | W2: Sin promocion | X2: FALSE | Z2: FALSE | AA2: FALSE | AB2: 20.1 | AC2: 5x4 | AD2: Domingo | AE2: 51.82 | AF2: 20 | AG2: 22.08 | AH2: SKU real | AI2: SKU real | AJ2: Alta | AK2: 0.35 | AL2: -0.69945786 | AM2: 28 | AN2: 0.77777778 | AO2: 0.99538689 | AP2: 50.38 | AQ2: 59.97 | AR2: 9.59 | AS2: 17.57 | AT2: 18.31 | AU2: 0.74
A3: 9 | B3: 11306 | C3: Sopa de Codo #2 La Moderna 200g | D3: Despensa | E3: Sopas, Pastas y Purés | F3: 7.24 | G3: 0 | H3: 0 | I3: 41 | J3: 12.27 | K3: Mayor a 40% | L3: Mas caro | M3: 10 | N3: 10 | O3: Mas caro | P3: Alta rotacion | Q3: BAJO SHARE | R3: ALTAMENTE ELASTICO | S3: 2.95 | T3: 0.8 | U3: 2.3 | V3: Categoria x tienda | W3: Sin promocion | X3: FALSE | Z3: FALSE | AA3: FALSE | AB3: 24.4 | AC3: 5x4 | AD3: Domingo | AE3: 9.82 | AF3: 20 | AG3: 26.25 | AH3: SKU real | AI3: SKU real | AJ3: Alta | AK3: 0.35 | AL3: -2.0773553 | AM3: 83 | AN3: 1.3015873 | AO3: 2.383131 | AP3: 15.97 | AQ3: 27.19 | AR3: 11.22 | AS3: 6.55 | AT3: 9.94 | AU3: 3.39
A4: 9 | B4: 26256 | C4: Barra de Proteína Wild Protein Chocolate Amargo 225g | D4: Despensa | E4: Cereales y Barras | F4: 97.22 | G4: 8 | H4: 0 | I4: 30.32 | J4: 150.68 | K4: 30% - 40% | L4: Mas caro | M4: 122.15 | N4: 147.75 | O4: Parity | P4: Alta rotacion | Q4: ALTO SHARE | R4: ALTAMENTE ELASTICO | S4: 1.6 | T4: 3 | U4: 4.9 | V4: Categoria x tienda | W4: Sin promocion | X4: FALSE | Z4: FALSE | AA4: FALSE | AB4: 10.7 | AC4: BNSDP: 2 uds, ahorra $15 c/u | AD4: Domingo | AE4: 135.68 | AF4: 10 | AG4: 22.62 | AH4: SKU real | AI4: SKU real | AJ4: Alta | AK4: 0.55 | AL4: -1.3062965 | AM4: 26 | AN4: 0.32804233 | AO4: 0.41331792 | AP4: 49.43 | AQ4: 58.87 | AR4: 9.44 | AS4: 13.88 | AT4: 14.33 | AU4: 0.45
A5: 9 | B5: 10458 | C5: Spaghetti La Moderna 200g | D5: Despensa | E5: Sopas, Pastas y Purés | F5: 7.84 | G5: 0 | H5: 0 | I5: 32.97 | J5: 11.7 | K5: 30% - 40% | L5: Mas caro | M5: 10.5 | N5: 13.62 | O5: Mas barato | P5: Alta rotacion | Q5: BAJO SHARE | R5: POCO ELASTICO | S5: 3 | T5: 0.8 | U5: 2.3 | V5: Categoria x tienda | W5: Sin promocion | X5: FALSE | Z5: FALSE | AA5: FALSE | AB5: 14.1 | AC5: BNSP: 3 x $33 | AD5: Domingo | AE5: 11 | AF5: 6 | AG5: 28.71 | AH5: SKU real | AI5: SKU real | AJ5: Alta | AK5: 0.4 | AL5: -0.93255994 | AM5: 11 | AN5: 1.3227513 | AO5: 1.4702833 | AP5: 15.48 | AQ5: 16.79 | AR5: 1.31 | AS5: 5.1 | AT5: 5.26 | AU5: 0.16
A6: 9 | B6: 12230 | C6: Mermelada de Fresa Smucker's Reducida en Azúcar 440g | D6: Despensa | E6: Untables y Miel | F6: 42.11 | G6: 0 | H6: 0 | I6: 54.42 | J6: 92.39 | K6: Mayor a 40% | L6: Mas barato | M6: 98 | N6: 98 | O6: Mas barato | P6: Alta rotacion | Q6: BAJO SHARE | R6: POCO ELASTICO | S6: 0.31 | T6: 17.2 | U6: 5.2 | V6: Categoria x tienda | W6: Sin promocion | X6: FALSE | Z6: TRUE | AA6: FALSE | AB6: 41.6 | AC6: SPON: 2 uds, -5% | AD6: Domingo | AE6: 87.77 | AF6: 5 | AG6: 52.02 | AH6: SKU real | AI6: SKU real | AJ6: Media | AK6: 0.55 | AL6: -0.77993435 | AM6: 8 | AN6: 0.058201058 | AO6: 0.062740359 | AP6: 5.38 | AQ6: 5.64 | AR6: 0.26 | AS6: 2.93 | AT6: 3 | AU6: 0.07
A7: 9 | B7: 13597 | C7: Sal Rosa del Himalaya White Sea 400g | D7: Despensa | E7: Especias y Condimentos | F7: 29.83 | G7: 0 | H7: 0 | I7: 38.63 | J7: 48.61 | K7: 30% - 40% | L7: Mas caro | M7: 45.67 | N7: 49.72 | O7: Mas barato | P7: Rotacion normal | Q7: BAJO SHARE | R7: POCO ELASTICO | S7: 1.79 | T7: 2.7 | U7: 4.8 | V7: Categoria x tienda | W7: Sin promocion | X7: FALSE | Z7: FALSE | AA7: FALSE | AB7: 21.3 | AC7: SPON: 2 uds, -5% | AD7: Domingo | AE7: 46.18 | AF7: 5 | AG7: 35.4 | AH7: SKU real | AI7: SKU real | AJ7: Alta | AK7: 0.55 | AL7: -0.89790132 | AM7: 9 | AN7: 0.37566138 | AO7: 0.40939206 | AP7: 18.26 | AQ7: 19.35 | AR7: 1.09 | AS7: 7.05 | AT7: 7.14 | AU7: 0.09
A8: 14 | B8: 12599 | C8: Yerba Mate Rosamonte 500g | D8: Despensa | E8: Café, Chocolate y Té | F8: 68.5 | G8: 0 | H8: 0 | I8: 39 | J8: 112.3 | K8: 30% - 40% | L8: Mas caro | M8: 104.27 | N8: 126 | O8: Mas barato | P8: Alta rotacion | Q8: ALTO SHARE | R8: ELASTICO | S8: 1.14 | T8: 1.9 | U8: 2.2 | V8: Categoria x tienda | W8: Sin promocion | X8: FALSE | Z8: FALSE | AA8: FALSE | AB8: 21.8 | AC8: 5x4 | AD8: Domingo | AE8: 89.84 | AF8: 20 | AG8: 23.75 | AH8: SKU real | AI8: SKU real | AJ8: Alta | AK8: 0.35 | AL8: -0.86928019 | AM8: 35 | AN8: 0.51322751 | AO8: 0.69168292 | AP8: 57.64 | AQ8: 72.24 | AR8: 14.6 | AS8: 22.48 | AT8: 24.86 | AU8: 2.38
A9: 14 | B9: 14258 | C9: Cereal Kellogg's Choco Krispis Original 290g | D9: Despensa | E9: Cereales y Barras | F9: 37.39 | G9: 8 | H9: 0 | I9: 37.66 | J9: 64.78 | K9: 30% - 40% | L9: Mas caro | M9: 47.99 | N9: 56 | O9: Mas caro | P9: Alta rotacion | Q9: ALTO SHARE | R9: POCO ELASTICO | S9: 3.77 | T9: 0.3 | U9: 1.1 | V9: Categoria x tienda | W9: Sin promocion | X9: FALSE | Z9: FALSE | AA9: FALSE | AB9: 20.1 | AC9: 5x4 | AD9: Domingo | AE9: 51.82 | AF9: 20 | AG9: 22.08 | AH9: SKU real | AI9: SKU real | AJ9: Alta | AK9: 0.35 | AL9: -1.042272 | AM9: 42 | AN9: 3.3068783 | AO9: 4.685545 | AP9: 214.22 | AQ9: 282.28 | AR9: 68.06 | AS9: 74.7 | AT9: 86.17 | AU9: 11.47
A10: 14 | B10: 11306 | C10: Sopa de Codo #2 La Moderna 200g | D10: Despensa | E10: Sopas, Pastas y Purés | F10: 7.24 | G10: 0 | H10: 0 | I10: 41 | J10: 12.27 | K10: Mayor a 40% | L10: Mas caro | M10: 10 | N10: 10 | O10: Mas caro | P10: Alta rotacion | Q10: BAJO SHARE | R10: ALTAMENTE ELASTICO | S10: 2.11 | T10: 0.3 | U10: 0.6 | V10: Categoria x tienda | W10: Sin promocion | X10: FALSE | Z10: FALSE | AA10: FALSE | AB10: 24.4 | AC10: 5x4 | AD10: Domingo | AE10: 9.82 | AF10: 20 | AG10: 26.25 | AH10: SKU real | AI10: SKU real | AJ10: Alta | AK10: 0.35 | AL10: -2.3632471 | AM10: 95 | AN10: 3.4761905 | AO10: 6.7622293 | AP10: 42.65 | AQ10: 77.16 | AR10: 34.51 | AS10: 17.49 | AT10: 28.21 | AU10: 10.72
A11: 14 | B11: 13597 | C11: Sal Rosa del Himalaya White Sea 400g | D11: Despensa | E11: Especias y Condimentos | F11: 29.83 | G11: 0 | H11: 0 | I11: 38.63 | J11: 48.61 | K11: 30% - 40% | L11: Mas caro | M11: 45.34 | N11: 50.27 | O11: Mas barato | P11: Alta rotacion | Q11: ALTO SHARE | R11: POCO ELASTICO | S11: 2.18 | T11: 0.6 | U11: 1.2 | V11: Categoria x tienda | W11: Sin promocion | X11: FALSE | Z11: FALSE | AA11: FALSE | AB11: 21.3 | AC11: 6x5 | AD11: Domingo | AE11: 40.51 | AF11: 16.7 | AG11: 26.35 | AH11: SKU real | AI11: SKU real | AJ11: Alta | AK11: 0.35 | AL11: -0.65008923 | AM11: 22 | AN11: 1.8042328 | AO11: 2.1952818 | AP11: 87.7 | AQ11: 100.49 | AR11: 12.79 | AS11: 33.88 | AT11: 35 | AU11: 1.12
A12: 14 | B12: 15858 | C12: Sal Rosa del Himalaya White Sea Molida 320g | D12: Despensa | E12: Especias y Condimentos | F12: 47.15 | G12: 0 | H12: 0 | I12: 38.84 | J12: 77.09 | K12: 30% - 40% | L12: Mas caro | M12: 71.23 | N12: 76.56 | O12: Parity | P12: Alta rotacion | Q12: ALTO SHARE | R12: POCO ELASTICO | S12: 1.04 | T12: 1.2 | U12: 1.2 | V12: Categoria x tienda | W12: Sin promocion | X12: FALSE | Z12: FALSE | AA12: FALSE | AB12: 21.6 | AC12: 6x5 | AD12: Domingo | AE12: 64.24 | AF12: 16.7 | AG12: 26.61 | AH12: SKU real | AI12: SKU real | AJ12: Alta | AK12: 0.35 | AL12: -0.74875943 | AM12: 25 | AN12: 0.86243386 | AO12: 1.0777287 | AP12: 66.49 | AQ12: 78.23 | AR12: 11.74 | AS12: 25.82 | AT12: 27.42 | AU12: 1.6
A13: 14 | B13: 26256 | C13: Barra de Proteína Wild Protein Chocolate Amargo 225g | D13: Despensa | E13: Cereales y Barras | F13: 97.22 | G13: 8 | H13: 0 | I13: 30.32 | J13: 150.68 | K13: 30% - 40% | L13: Mas caro | M13: 127.83 | N13: 150.73 | O13: Mas barato | P13: Alta rotacion | Q13: ALTO SHARE | R13: ALTAMENTE ELASTICO | S13: 1.75 | T13: 0.6 | U13: 1.1 | V13: Categoria x tienda | W13: Sin promocion | X13: FALSE | Z13: FALSE | AA13: FALSE | AB13: 10.7 | AC13: BNSDP: 2 uds, ahorra $15 c/u | AD13: Domingo | AE13: 135.68 | AF13: 10 | AG13: 22.62 | AH13: SKU real | AI13: SKU real | AJ13: Alta | AK13: 0.55 | AL13: -3.0333065 | AM13: 60 | AN13: 1.5396825 | AO13: 2.469078 | AP13: 232 | AQ13: 351.68 | AR13: 119.68 | AS13: 65.13 | AT13: 85.6 | AU13: 20.47
... A65: 14 | B65: 13214 | C65: Crema para Peinar Pantene Rizos Definidos 300ml | D65: Higiene Personal y Belleza | E65: Cuidado del Cabello | F65: 45.32 | G65: 0 | H65: 16 | I65: 31.64 | J65: 76.91 | K65: 30% - 40% | L65: Mas caro | M65: 64.35 | N65: 85.94 | O65: Mas barato | P65: Alta rotacion | Q65: BAJO SHARE | R65: POCO ELASTICO | S65: 2.08 | T65: 2.8 | U65: 5.9 | V65: Categoria x tienda | W65: Sin promocion | X65: FALSE | Z65: FALSE | AA65: FALSE | AB65: 12.4 | AC65: SPON: 2 uds, -5% | AD65: Viernes | AE65: 73.06 | AF65: 5 | AG65: 28.04 | AH65: SKU real | AI65: SKU real | AJ65: Alta | AK65: 0.55 | AL65: -1.3518588 | AM65: 14 | AN65: 0.35449735 | AO65: 0.40242039 | AP65: 27.26 | AQ65: 30.1 | AR65: 2.84 | AS65: 7.44 | AT65: 7.71 | AU65: 0.27
